Metadata-Version: 2.1
Name: git-show-bigfiles
Version: 1.0.1317
Summary: git bigfile detection
Home-page: https://github.com/gdraheim/git_show_bigfiles
Author: Guido U. Draheim
Author-email: Guido.Draheim@gmx.de
License: LGPL
Platform: UNKNOWN
